Biblio/__init__.py
Biblio/testinLib.py
allesLib-0.0.11.dist-info/METADATA
allesLib-0.0.11.dist-info/WHEEL
allesLib-0.0.11.dist-info/top_level.txt
allesLib-0.0.11.dist-info/RECORD
