Metadata-Version: 2.1
Name: allesLib
Version: 0.0.11
Summary: add, roll, lustig
Author: HomeCamper
Author-email: <huber.xittam@gmail.com>
Keywords: python
Classifier: Development Status :: 1 - Planning
Classifier: Intended Audience :: Developers
Classifier: Programming Language :: Python :: 3
Classifier: Operating System :: Unix
Classifier: Operating System :: MacOS :: MacOS X
Classifier: Operating System :: Microsoft :: Windows
